mathgen/__init__.py
mathgen/algebra.py
mathgen/calc1.py
mathgen/helper.py
mathgen-0.0.1.dist-info/DESCRIPTION.rst
mathgen-0.0.1.dist-info/METADATA
mathgen-0.0.1.dist-info/RECORD
mathgen-0.0.1.dist-info/WHEEL
mathgen-0.0.1.dist-info/metadata.json
mathgen-0.0.1.dist-info/top_level.txt
