Metadata-Version: 2.0
Name: mathgen
Version: 0.0.1
Summary: Generate random maths problems
Home-page: http://github.com/murenei/mathgen
Author: Richard Murray
Author-email: rick.j.murray@gmail.com
License: MIT
Platform: UNKNOWN
Classifier: Programming Language :: Python :: 3
Classifier: License :: OSI Approved :: MIT License
Classifier: Operating System :: OS Independent
Requires-Dist: sympy
